inverse_spectrogram/__init__.py
inverse_spectrogram/inverse_spectrogram.py
pyhon_inverse_spectrogram-0.0.2.dist-info/LICENSE
pyhon_inverse_spectrogram-0.0.2.dist-info/METADATA
pyhon_inverse_spectrogram-0.0.2.dist-info/WHEEL
pyhon_inverse_spectrogram-0.0.2.dist-info/top_level.txt
pyhon_inverse_spectrogram-0.0.2.dist-info/RECORD
