Metadata-Version: 2.1
Name: pyhon-inverse-spectrogram
Version: 0.0.2
Summary: Inverse spectogram for scipy.signal.spectrogram
Home-page: https://github.com/kummahiih/python-inverse-spectrogram
Author: Pauli Rikula
License: MIT
Platform: UNKNOWN
Classifier: License :: OSI Approved :: MIT License
Classifier: Programming Language :: Python :: 3.8
Requires-Python: ~=3.8
Requires-Dist: numpy (>=1.18.4)
Requires-Dist: scipy (>=1.4.1)
